{
    "party": "維新",
    "repr_name": "浅田均",
    "topic": "原発",
    "search_words": [
        "原子",
        "原発",
        "廃炉",
        "再稼働",
        "ベースロード"
    ],
    "speeches": [
        {
            "speech_id": "121114370X01020230525_180",
            "house_name": "参議院",
            "meeting_name": "財政金融委員会",
            "date": "2023-05-25",
            "speech_url": "https://kokkai.ndl.go.jp/txt/121114370X01020230525/180",
            "speaker_group": "日本維新の会",
            "extracted_opinions": [
                "\r\n　ただ、党の弁護しておくわけじゃないんですけど、核兵器を仮に、核議論やっていますけど、核兵器を持ってしまったならば、ＮＰＴ体制からは脱退する必要があるし、日米原子力協定もほごする必要あって、そのためにどれだけのお金が必要かというと、それは持たない方がいいだろうというのが私どもの党の考え方でございますんで、この際申し添えさせていただきます"
            ]
        },
        {
            "speech_id": "121115254X00420230127_006",
            "house_name": "参議院",
            "meeting_name": "本会議",
            "date": "2023-01-27",
            "speech_url": "https://kokkai.ndl.go.jp/txt/121115254X00420230127/6",
            "speaker_group": "日本維新の会",
            "extracted_opinions": [
                "\r\n　政府は、廃炉となる原発の次世代革新炉への建て替えや運転期間延長を進めるとしていますが、そのためには国の責任と覚悟が問われます",
                "これまでのエネルギー政策を大きく転換する中、国の責任について、最終処分事業の促進は当然のこと、再稼働早期化や事故時の賠償責任についても、より国が責任を持つ体制にしていくべきと考えます"
            ]
        },
        {
            "speech_id": "121015254X00320221007_008",
            "house_name": "参議院",
            "meeting_name": "本会議",
            "date": "2022-10-07",
            "speech_url": "https://kokkai.ndl.go.jp/txt/121015254X00320221007/8",
            "speaker_group": "日本維新の会",
            "extracted_opinions": [
                "\r\n　原発の再稼働が急務であることは論をまちませんが、総理は、エネルギー安定供給について、所信表明演説で既存原発の運転期限の延長について触れませんでしたが、検討項目には入っていないという理解でよいのでしょうか",
                "当面の原子力活用と再生可能エネルギーの促進は二律背反ではなく、脱炭素に向けても重要な取組です"
            ]
        },
        {
            "speech_id": "120815254X00320220121_010",
            "house_name": "参議院",
            "meeting_name": "本会議",
            "date": "2022-01-21",
            "speech_url": "https://kokkai.ndl.go.jp/txt/120815254X00320220121/10",
            "speaker_group": "日本維新の会",
            "extracted_opinions": [
                "これまで、原子力と天然ガスについては、ＥＵ内ではいまだ原発廃止を主張する国もあるため意見が分かれてきましたが、ＥＵが一定の方針を示したものと言えます",
                "従来のように遠隔地で大規模発電をして、電力ロスを多量に出しながら消費地に電力を引っ張ってくるのではなく、地産地消型の電力として小型原子炉を検討する時期が来ていると考えます",
                "原子力発電に対する考え方を改めるべきではないでしょうか"
            ]
        },
        {
            "speech_id": "120715254X00320211210_010",
            "house_name": "参議院",
            "meeting_name": "本会議",
            "date": "2021-12-10",
            "speech_url": "https://kokkai.ndl.go.jp/txt/120715254X00320211210/10",
            "speaker_group": "日本維新の会",
            "extracted_opinions": [
                "その基地内に、例えば、我が国にある米軍基地、霞が関あるいは原子力発電所等の重要インフラをターゲットとする核弾頭搭載ミサイルの発射プログラムを発見した場合、これを無力化することは敵基地攻撃に該当するのか、サイバー防衛というのならここまで考えておく必要があると思います"
            ]
        },
        {
            "speech_id": "120315261X00220201106_120",
            "house_name": "参議院",
            "meeting_name": "予算委員会",
            "date": "2020-11-06",
            "speech_url": "https://kokkai.ndl.go.jp/txt/120315261X00220201106/120",
            "speaker_group": "日本維新の会",
            "extracted_opinions": [
                "\r\n　福島第一原発を契機として首都機能、代替機能というものを備えようとしたのが日本銀行とＮＨＫと気象庁であるというふうに承知しておりますけれども、そのほかの機関も、そういう首都代替機能、機能が麻痺しないビジネスコンティニュイティーといいますか、そういうものをお考えいただけたらと思っております"
            ]
        },
        {
            "speech_id": "120015261X00220191016_225",
            "house_name": "参議院",
            "meeting_name": "予算委員会",
            "date": "2019-10-16",
            "speech_url": "https://kokkai.ndl.go.jp/txt/120015261X00220191016/225",
            "speaker_group": "日本維新の会",
            "extracted_opinions": [
                "\r\n　我が党は、衆議院の予算委員会でも、福島第一原発の処理水は、これまでに海洋放出されてきた処理水と科学的に何ら変わりなく、健康被害は想定できない、国内はもちろんのこと、韓国始め世界の国々に対し、福島第一原発の処理水が世界各地の原子力施設、ここが重要なんですよ、原子力施設を申し上げております、単に原発だけでなく再処理工場もこれ含むんです、だから原子力施設と申し上げております、から放出されてきました処理水と科学的には何ら変わりないということを丁寧に説明した上で、できるだけ早く海洋放出の決断をすべきと申し上げました"
            ]
        },
        {
            "speech_id": "119614396X00120180207_050",
            "house_name": "参議院",
            "meeting_name": "資源エネルギーに関する調査会",
            "date": "2018-02-07",
            "speech_url": "https://kokkai.ndl.go.jp/txt/119614396X00120180207/50",
            "speaker_group": "日本維新の会",
            "extracted_opinions": [
                "脱化石燃料で脱原発依存という二つを実現させようと思うとエネルギー供給源が全くなくなってしまうということに、困ったことになりまして、トリレンマ以上のものが私たちに課題として突き付けられるわけでありますけれども"
            ]
        },
        {
            "speech_id": "119313950X02720170615_123",
            "house_name": "参議院",
            "meeting_name": "外交防衛委員会",
            "date": "2017-06-15",
            "speech_url": "https://kokkai.ndl.go.jp/txt/119313950X02720170615/123",
            "speaker_group": "日本維新の会",
            "extracted_opinions": [
                "外務大臣に日本の原子力制度から年金制度から何から何まで、将来そういう立場に立たれる可能性もありますのでこの際勉強しておいていただいたらいいのかなと思ってこういう質問をさせていただいておるわけでありますが、まあ、お仲間ですから、ほかの省庁に対して疑いの目で見るというのはちょっと難しいかと思うんですけれども、私どもは、平成三十何年頃になるとちょっと危なく、怪しくなってくるというふうな試算をしておりますので、これから厚労省から何か情報を得られるときは批判的な目で見ていただきたいと思います"
            ]
        },
        {
            "speech_id": "119313950X02420170606_218",
            "house_name": "参議院",
            "meeting_name": "外交防衛委員会",
            "date": "2017-06-06",
            "speech_url": "https://kokkai.ndl.go.jp/txt/119313950X02420170606/218",
            "speaker_group": "日本維新の会",
            "extracted_opinions": [
                "日米原子力協定に基づいて日本からアメリカへ持っていって、アメリカで物を造って、それをインドへ持っていったということに関しては、これはインドとアメリカの関係であって日本は関わりがないという立場ですか"
            ]
        },
        {
            "speech_id": "119313950X02420170606_244",
            "house_name": "参議院",
            "meeting_name": "外交防衛委員会",
            "date": "2017-06-06",
            "speech_url": "https://kokkai.ndl.go.jp/txt/119313950X02420170606/244",
            "speaker_group": "日本維新の会",
            "extracted_opinions": [
                "\r\n　私たちは、経済合理性から考えて、原子力発電というのは、廃炉費用とかも、で、安全性を高めることによって建設コストが必ずしも安くないと、クリーンなエネルギーということは認めますけれども、一番安価なエネルギーではないというふうになると思っております",
                "したがって、原子力発電というのはやがてフェードアウトしていくだろうというふうな考え方に立っております",
                "それから、ノーチラス号という原子力潜水艦ができて、小型の軽水炉ですよね、それが陸上に上がって原子力発電として平和利用されているということで、大型軽水炉あるいは原子力発電所が全部なくなってしまったとしても、原子力の平和利用とか原子力技術を維持していくということは私たちは必要なことであると思っております",
                "\r\n　だから、原子力発電所によることなくこの原子力技術を維持していくための一つの方法として、原子力潜水艦、海から陸に上がってきたやつをまた陸から海に戻すというだけの話なんですが、原子力潜水艦を建造して、そこで原子力技術を維持向上させていくという可能性があると思っているんですけれども、防衛大臣は、原子力潜水艦を建造するということに何か障害があるとお考えでしょうか"
            ]
        },
        {
            "speech_id": "119313950X02320170601_138",
            "house_name": "参議院",
            "meeting_name": "外交防衛委員会",
            "date": "2017-06-01",
            "speech_url": "https://kokkai.ndl.go.jp/txt/119313950X02320170601/138",
            "speaker_group": "日本維新の会",
            "extracted_opinions": [
                "これが我が国が抱えておる原発問題の実態だと思っております"
            ]
        },
        {
            "speech_id": "119313950X02320170601_142",
            "house_name": "参議院",
            "meeting_name": "外交防衛委員会",
            "date": "2017-06-01",
            "speech_url": "https://kokkai.ndl.go.jp/txt/119313950X02320170601/142",
            "speaker_group": "日本維新の会",
            "extracted_opinions": [
                "\r\n　こういう事実があるにもかかわらず、フランスのＡＳＴＲＩＤの方に行かれているということで、今申し上げましたアメリカのアルゴンヌ国立研究所で開発されていた統合型高速炉、ＩＦＲについての評価をお伺いしたいんですが、これ、本当に実用化されていて、福島原発で同じような仕組みが導入されていたら、全電源喪失でも自動的に炉は停止すると、それと核燃料サイクルにも貢献できるということで、話だけ聞いていたら理想的な炉であると思うんですけれども、アメリカはそういうのを中断してしまったと"
            ]
        },
        {
            "speech_id": "119313950X02220170530_057",
            "house_name": "参議院",
            "meeting_name": "外交防衛委員会",
            "date": "2017-05-30",
            "speech_url": "https://kokkai.ndl.go.jp/txt/119313950X02220170530/57",
            "speaker_group": "日本維新の会",
            "extracted_opinions": [
                "\r\n　それで、今、仮に日本とできなくても、ロシアとかオーストラリアとは可能であるというお話をいただきまして、ロシアは終了規定がないというお話もありましたけれども、仮にインドがロシアとそういう原子力発電所の売買に関して関係が強くなったとした場合、インドとロシアの関係が強化することによってその周辺国に対する地政学的な影響というものはどのようなものが考えられるのか、ちょっと教えていただきたいんですが"
            ]
        },
        {
            "speech_id": "119313950X02220170530_061",
            "house_name": "参議院",
            "meeting_name": "外交防衛委員会",
            "date": "2017-05-30",
            "speech_url": "https://kokkai.ndl.go.jp/txt/119313950X02220170530/61",
            "speaker_group": "日本維新の会",
            "extracted_opinions": [
                "\r\n　私たち日本維新の会は、エネルギーミックスというか、原発の割合を、これからその廃炉費用等も考えますと、今までのように一番安いエネルギーではなくなるだろうと"
            ]
        },
        {
            "speech_id": "119313950X02220170530_053",
            "house_name": "参議院",
            "meeting_name": "外交防衛委員会",
            "date": "2017-05-30",
            "speech_url": "https://kokkai.ndl.go.jp/txt/119313950X02220170530/53",
            "speaker_group": "日本維新の会",
            "extracted_opinions": [
                "当然のことながら、原発の数を増やすということはもうそれだけ原発リスクが高くなるということでありまして、そういう原発リスクが増大するというマイナスの面があって、他方、経済発展ではプラスの面があるという判断からこういう数字を挙げておられるんだろうと思います"
            ]
        },
        {
            "speech_id": "119313950X02020170523_127",
            "house_name": "参議院",
            "meeting_name": "外交防衛委員会",
            "date": "2017-05-23",
            "speech_url": "https://kokkai.ndl.go.jp/txt/119313950X02020170523/127",
            "speaker_group": "日本維新の会",
            "extracted_opinions": [
                "例えば、原発というか原子力発電システム系に重大な影響を及ぼす、そういうサイバー攻撃がなされたと、明確に北朝鮮が、うちが日本を攻撃するんやという前提の下に、宣言の下にそういう攻撃がなされたと、そういうときに自衛権は行使できるんですか"
            ]
        },
        {
            "speech_id": "119213950X00420161027_034",
            "house_name": "参議院",
            "meeting_name": "外交防衛委員会",
            "date": "2016-10-27",
            "speech_url": "https://kokkai.ndl.go.jp/txt/119213950X00420161027/34",
            "speaker_group": "日本維新の会",
            "extracted_opinions": [
                "申し上げましたように、知事にそういう止める権限はないんですけれども、地元理解を得るという意味では、そういう再稼働反対派の知事が誕生しつつあるということは逆風になると思います"
            ]
        },
        {
            "speech_id": "119213950X00320161025_212",
            "house_name": "参議院",
            "meeting_name": "外交防衛委員会",
            "date": "2016-10-25",
            "speech_url": "https://kokkai.ndl.go.jp/txt/119213950X00320161025/212",
            "speaker_group": "日本維新の会",
            "extracted_opinions": [
                "\r\n　こういう前提を踏まえて考えますと、原子力のここに掲げられています二二から二〇というのは、私どもは到底納得できる数字ではないんですが、この点いかがですか"
            ]
        }
    ]
}