{
    "party": "自民",
    "repr_name": "小林鷹之",
    "topic": "原発",
    "search_words": [
        "原子",
        "原発",
        "廃炉",
        "再稼働",
        "ベースロード"
    ],
    "speeches": [
        {
            "speech_id": "121005261X00220221017_082",
            "house_name": "衆議院",
            "meeting_name": "予算委員会",
            "date": "2022-10-17",
            "speech_url": "https://kokkai.ndl.go.jp/txt/121005261X00220221017/82",
            "speaker_group": "自由民主党",
            "extracted_opinions": [
                "\r\n　現行のエネルギー基本計画では、可能な限り原発依存度を低減するとされている中で、総理がリーダーシップを発揮されて、原発再稼働や次世代革新炉の開発、建設について検討すると判断されたことを私は強く支持いたします"
            ]
        },
        {
            "speech_id": "120804889X01220220325_244",
            "house_name": "衆議院",
            "meeting_name": "内閣委員会",
            "date": "2022-03-25",
            "speech_url": "https://kokkai.ndl.go.jp/txt/120804889X01220220325/244",
            "speaker_group": "自由民主党",
            "extracted_opinions": [
                "\r\n　したがって、安定供給を確保するというのは当然だと思っておりまして、その上で、エネルギー政策は、安全性を大前提とした上で、安定供給、経済効率性、そして環境適合を同時に達成すべく取組が進められてきたと承知をしていますが、これらの要素全て満たす単一の完璧なエネルギー源というのはないと考えておりまして、一つのエネルギー源に頼ることはリスクが高いですし、危機時であっても安定供給を確保し続けるためには、原子力を含めたバランスの取れた供給構造を実現することが必要だと思っています",
                "\r\n　私は経済安保担当大臣という立場ですけれども、私としては、安定供給の確保を図る観点から、安全性の確保を大前提とした上で、原子力発電所の再稼働を着実に進めることが重要だと考えています"
            ]
        },
        {
            "speech_id": "120804889X01220220325_332",
            "house_name": "衆議院",
            "meeting_name": "内閣委員会",
            "date": "2022-03-25",
            "speech_url": "https://kokkai.ndl.go.jp/txt/120804889X01220220325/332",
            "speaker_group": "自由民主党",
            "extracted_opinions": [
                "\r\n　そうした観点からは、今、これらの要素を全て満たす単一の完璧なエネルギー源がない現状では、安全性の確保を大前提とした上で、原子力発電所の再稼働を着実に進めることが重要だと考えています"
            ]
        },
        {
            "speech_id": "120405354X00120210318_002",
            "house_name": "衆議院",
            "meeting_name": "経済産業委員会原子力問題調査特別委員会連合審査会",
            "date": "2021-03-18",
            "speech_url": "https://kokkai.ndl.go.jp/txt/120405354X00120210318/2",
            "speaker_group": "自由民主党・無所属の会",
            "extracted_opinions": [
                "\r\n　私たちは、福島第一原発の事故を経験して以来、原発については、その再稼働を含めて、国民との信頼関係こそが基本であることを学んできたはずであります",
                "\r\n　私の地元千葉県には原発はございません"
            ]
        },
        {
            "speech_id": "120405354X00120210318_004",
            "house_name": "衆議院",
            "meeting_name": "経済産業委員会原子力問題調査特別委員会連合審査会",
            "date": "2021-03-18",
            "speech_url": "https://kokkai.ndl.go.jp/txt/120405354X00120210318/4",
            "speaker_group": "自由民主党・無所属の会",
            "extracted_opinions": [
                "\r\n　今回の案件をめぐり、明確にしなければならないと思うことは、東電特有の問題として捉えるべきなのか、あるいは我が国の原子力業界全体の問題として捉えるべきなのか、その点でございます"
            ]
        },
        {
            "speech_id": "120405354X00120210318_008",
            "house_name": "衆議院",
            "meeting_name": "経済産業委員会原子力問題調査特別委員会連合審査会",
            "date": "2021-03-18",
            "speech_url": "https://kokkai.ndl.go.jp/txt/120405354X00120210318/8",
            "speaker_group": "自由民主党・無所属の会",
            "extracted_opinions": [
                "安全第一を旨とする原子力発電だからこそ、この事実を正確に報告すべきだと考えますので、是非そこは検討いただきたいと思います"
            ]
        },
        {
            "speech_id": "120405354X00120210318_014",
            "house_name": "衆議院",
            "meeting_name": "経済産業委員会原子力問題調査特別委員会連合審査会",
            "date": "2021-03-18",
            "speech_url": "https://kokkai.ndl.go.jp/txt/120405354X00120210318/14",
            "speaker_group": "自由民主党・無所属の会",
            "extracted_opinions": [
                "\r\n　エネルギー産業は、各産業の中でも最も重要な産業の一つであって、原子力産業というのはその中でも一番重要な産業の一つだと思います"
            ]
        },
        {
            "speech_id": "120405271X00120210225_078",
            "house_name": "衆議院",
            "meeting_name": "予算委員会第七分科会",
            "date": "2021-02-25",
            "speech_url": "https://kokkai.ndl.go.jp/txt/120405271X00120210225/78",
            "speaker_group": "自由民主党・無所属の会",
            "extracted_opinions": [
                "\r\n　次に、第六次エネ基についてなんですけれども、先ほど申し上げたとおり、国ごとに置かれている状況が違うということを踏まえて作成をいただければと思いますが、時間の関係がありますのでちょっとはしょっていきますと、例えば欧州を見たときに、フランスなんかはもう原子力が七割超えているのでちょっと参考にならないですけれども、例えばドイツなんかは電源構成が日本に近くて自給率も高くない、しかも、今後、石炭と原子力の割合を減らしていくという方向性は何となく似ている"
            ]
        },
        {
            "speech_id": "120405271X00120210225_080",
            "house_name": "衆議院",
            "meeting_name": "予算委員会第七分科会",
            "date": "2021-02-25",
            "speech_url": "https://kokkai.ndl.go.jp/txt/120405271X00120210225/80",
            "speaker_group": "自由民主党・無所属の会",
            "extracted_opinions": [
                "\r\n　我が国においてカーボンニュートラルを実現するには、原発が絶対不可欠だと私は思います",
                "グリーン成長戦略で原子力について可能な限り依存度を低減すると書いてあるのが、若干、ミスリーディングに思います",
                "原子力に対する国民的理解を更に前進させる観点からも、是非、これから大臣を筆頭に、六次のエネ基がありますので、そこにしっかりとしたメッセージを書き込めるように頑張っていただきたいと思います",
                "\r\n　質疑時間が終了しましたので、もう答弁は求めませんけれども、この原子力の話と、また、今、再エネ、私も推進すべきだと思いますが、内閣府の規制改革タスクフォースなどで若干、緩和にちょっと重きを置き過ぎた議論が走っているように私個人は受け止めておりまして、規制改革といったときに、緩和だけではなくて、やはりいろいろな意味で強化をすべき点もあるというふうに思いますので、その点については政府一体となって検討いただければと思います"
            ]
        },
        {
            "speech_id": "119804080X00220190313_022",
            "house_name": "衆議院",
            "meeting_name": "経済産業委員会",
            "date": "2019-03-13",
            "speech_url": "https://kokkai.ndl.go.jp/txt/119804080X00220190313/22",
            "speaker_group": "自由民主党",
            "extracted_opinions": [
                "\r\n　第五次エネ基では、原子力は重要なベースロード電源と位置づけられる一方で、大臣所信では、依存度を可能な限り低減していく方針ということで、今後、原発について国としてどう向き合っていくのかが、やや私はわかりにくいというふうに感じています",
                "\r\n　私としては、電力価格の低減ですとかエネルギー安保、あるいは温室効果ガスの抑制、高度な技術を通じた海外貢献、こうした観点から、原子力政策を国策として、より明確に位置づけていくべきだと考えています",
                "\r\n　国内では再稼働が進んでいないし、海外案件も事実上ゼロになった今、特に、原子力の技術の承継や技術者の育成は喫緊の課題だと思います",
                "原子力に未来や希望がないとすれば、大学などで原子力を専攻する学生は減少の一途をたどるでしょうし、そうなれば、高い技術と長い期間を要する廃炉すら、円滑に行うことは私は困難になっていくと思います",
                "\r\n　もちろん国民による原発の安全性、必要性に対する理解は大前提なので、民間事業者などで構成される、ＡＴＥＮＡと呼ばれる組織がありますけれども、こうした組織が速やかに確立をされ、規制当局との対話を通じて、科学的知見に基づいた冷静な議論がこれから透明性を持って行われることを期待をしています",
                "\r\n　ちょっと時間が来ていますので一つ飛ばさせていただきますけれども、私個人の意見としては、国内で再稼働を進めていくことはもとより、第五次エネルギー基本計画に盛り込まれなかったリプレースや新増設についても、安全性をしっかりと確保した上で、国が一歩踏み込んで進めていくべきだと思っております",
                "また、今後もインフラシステム輸出の柱として原発を位置づけるという理解でよろしいでしょうか"
            ]
        },
        {
            "speech_id": "119804080X00220190313_024",
            "house_name": "衆議院",
            "meeting_name": "経済産業委員会",
            "date": "2019-03-13",
            "speech_url": "https://kokkai.ndl.go.jp/txt/119804080X00220190313/24",
            "speaker_group": "自由民主党",
            "extracted_opinions": [
                "\r\n　そこで伺いたいんですけれども、エネルギー安全保障という枠組みを超えて、我が国の外交政策上の観点からも、国策としての原発輸出を検討すべきであると私は考えておりますが、残念ながら、ＮＳＣなどの場で議論された形跡が見えません"
            ]
        }
    ]
}