{
    "party": "立憲",
    "repr_name": "末松義規",
    "topic": "少子化",
    "search_words": [
        "出生率",
        "少子化",
        "子育て支援",
        "育児支援",
        "学費"
    ],
    "speeches": [
        {
            "speech_id": "117714323X00320110216_021",
            "house_name": "参議院",
            "meeting_name": "国民生活・経済・社会保障に関する調査会",
            "date": "2011-02-16",
            "speech_url": "https://kokkai.ndl.go.jp/txt/117714323X00320110216/21",
            "speaker_group": "民主党・無所属クラブ",
            "extracted_opinions": [
                "そこで、いろいろと女性に聞いてみた場合に、やっぱり子供を産んでも仕事を続けたい、でも子供を産んでしまうと仕事が続けられない、そういった意味で保育所等があればそれはいいのになということで、それで保育所を増やして、まあ第一義的には両親の子育ての義務があるんですけれども、それを社会的全体で社会で負担するという中で保育所等が拡大していけば、それは子供を産むというインセンティブが御両親の間で生まれると、こういうことで少子化対策になると、こういうことと理解をしております",
                "セーフティーネットの低下とか、あるいは医療・介護サービスの提供体制の劣化とか、あるいは少子化への取組の遅れとか、こういった問題を機能として新たにこれらに、解決するような、そういう高機能なことをこの社会保障ということに含めていくと、こういうのが私どもが使ってきたこの高機能ということだと私は理解しております"
            ]
        }
    ]
}